{
  "projectRoot": "/Users/joohwan/GolandProjects/infra",
  "batchFiles": [
    {"path": "packages/local-dev/Makefile", "language": "makefile", "sizeLines": 15, "fileCategory": "infra"},
    {"path": "packages/local-dev/docker-compose.yaml", "language": "yaml", "sizeLines": 131, "fileCategory": "infra"},
    {"path": "packages/local-dev/go.mod", "language": "mod", "sizeLines": 88, "fileCategory": "config"},
    {"path": "packages/local-dev/go.sum", "language": "sum", "sizeLines": 214, "fileCategory": "config"},
    {"path": "packages/local-dev/grafana-datasources.yaml", "language": "yaml", "sizeLines": 44, "fileCategory": "config"},
    {"path": "packages/local-dev/mimir.yaml", "language": "yaml", "sizeLines": 43, "fileCategory": "config"},
    {"path": "packages/local-dev/otel-collector.yaml", "language": "yaml", "sizeLines": 73, "fileCategory": "config"},
    {"path": "packages/local-dev/tempo.yaml", "language": "yaml", "sizeLines": 96, "fileCategory": "config"},
    {"path": "packages/local-dev/vector.toml", "language": "toml", "sizeLines": 112, "fileCategory": "config"}
  ],
  "batchImportData": {
    "packages/local-dev/Makefile": [],
    "packages/local-dev/docker-compose.yaml": [],
    "packages/local-dev/go.mod": [],
    "packages/local-dev/go.sum": [],
    "packages/local-dev/grafana-datasources.yaml": [],
    "packages/local-dev/mimir.yaml": [],
    "packages/local-dev/otel-collector.yaml": [],
    "packages/local-dev/tempo.yaml": [],
    "packages/local-dev/vector.toml": []
  }
}
