{
  "scriptCompleted": true,
  "filesAnalyzed": 7,
  "filesSkipped": [],
  "results": [
    {
      "path": "iac/provider-aws/Makefile",
      "language": "makefile",
      "fileCategory": "infra",
      "totalLines": 118,
      "nonEmptyLines": 100,
      "steps": [
        {
          "name": "provider-login",
          "startLine": 57,
          "endLine": 59
        },
        {
          "name": "switch",
          "startLine": 61,
          "endLine": 63
        },
        {
          "name": "init",
          "startLine": 65,
          "endLine": 75
        },
        {
          "name": "plan",
          "startLine": 77,
          "endLine": 81
        },
        {
          "name": "plan-only-jobs",
          "startLine": 85,
          "endLine": 89
        },
        {
          "name": "plan-without-jobs",
          "startLine": 91,
          "endLine": 95
        },
        {
          "name": "apply",
          "startLine": 97,
          "endLine": 100
        },
        {
          "name": "state-migrate",
          "startLine": 102,
          "endLine": 105
        },
        {
          "name": "apply-init",
          "startLine": 107,
          "endLine": 109
        },
        {
          "name": "move",
          "startLine": 111,
          "endLine": 114
        },
        {
          "name": "destroy",
          "startLine": 116,
          "endLine": 119
        }
      ],
      "metrics": {
        "importCount": 0,
        "exportCount": 0,
        "functionCount": 0,
        "classCount": 0,
        "stepCount": 11
      }
    },
    {
      "path": "iac/provider-aws/alb.tf",
      "language": "terraform",
      "fileCategory": "infra",
      "totalLines": 183,
      "nonEmptyLines": 151,
      "resources": [
        {
          "name": "aws_security_group.ingress",
          "kind": "aws_security_group",
          "startLine": 1,
          "endLine": 34
        },
        {
          "name": "aws_lb.ingress",
          "kind": "aws_lb",
          "startLine": 36,
          "endLine": 50
        },
        {
          "name": "aws_lb_listener.ingress_redirect",
          "kind": "aws_lb_listener",
          "startLine": 52,
          "endLine": 67
        },
        {
          "name": "aws_lb_listener.ingress_wildcard",
          "kind": "aws_lb_listener",
          "startLine": 69,
          "endLine": 82
        },
        {
          "name": "aws_lb_listener_rule.ingress_grpc",
          "kind": "aws_lb_listener_rule",
          "startLine": 84,
          "endLine": 99
        },
        {
          "name": "aws_lb_listener_rule.nomad",
          "kind": "aws_lb_listener_rule",
          "startLine": 101,
          "endLine": 117
        },
        {
          "name": "aws_lb_target_group.ingress",
          "kind": "aws_lb_target_group",
          "startLine": 119,
          "endLine": 139
        },
        {
          "name": "aws_lb_target_group.ingress_grpc",
          "kind": "aws_lb_target_group",
          "startLine": 141,
          "endLine": 161
        },
        {
          "name": "aws_lb_target_group.nomad",
          "kind": "aws_lb_target_group",
          "startLine": 163,
          "endLine": 183
        }
      ],
      "metrics": {
        "importCount": 0,
        "exportCount": 0,
        "functionCount": 0,
        "classCount": 0,
        "definitionCount": 0,
        "resourceCount": 9
      }
    },
    {
      "path": "iac/provider-aws/alb_athena.tf",
      "language": "terraform",
      "fileCategory": "infra",
      "totalLines": 233,
      "nonEmptyLines": 188,
      "resources": [
        {
          "name": "aws_glue_catalog_database.ingress_load_balancer_logs",
          "kind": "aws_glue_catalog_database",
          "startLine": 10,
          "endLine": 13
        },
        {
          "name": "aws_glue_catalog_table.ingress_load_balancer_logs",
          "kind": "aws_glue_catalog_table",
          "startLine": 15,
          "endLine": 219
        },
        {
          "name": "aws_athena_workgroup.operations",
          "kind": "aws_athena_workgroup",
          "startLine": 221,
          "endLine": 233
        },
        {
          "name": "data.aws_s3_bucket.load_balancer_logs",
          "kind": "data.aws_s3_bucket",
          "startLine": 6,
          "endLine": 8
        }
      ],
      "metrics": {
        "importCount": 0,
        "exportCount": 0,
        "functionCount": 0,
        "classCount": 0,
        "definitionCount": 0,
        "resourceCount": 4
      }
    },
    {
      "path": "iac/provider-aws/domain.tf",
      "language": "terraform",
      "fileCategory": "infra",
      "totalLines": 49,
      "nonEmptyLines": 41,
      "resources": [
        {
          "name": "aws_acm_certificate.wildcard",
          "kind": "aws_acm_certificate",
          "startLine": 13,
          "endLine": 20
        },
        {
          "name": "aws_acm_certificate_validation.wildcard",
          "kind": "aws_acm_certificate_validation",
          "startLine": 22,
          "endLine": 24
        },
        {
          "name": "cloudflare_record.cert",
          "kind": "cloudflare_record",
          "startLine": 26,
          "endLine": 40
        },
        {
          "name": "cloudflare_record.routing",
          "kind": "cloudflare_record",
          "startLine": 42,
          "endLine": 49
        },
        {
          "name": "data.cloudflare_zone.domain",
          "kind": "data.cloudflare_zone",
          "startLine": 9,
          "endLine": 11
        }
      ],
      "metrics": {
        "importCount": 0,
        "exportCount": 0,
        "functionCount": 0,
        "classCount": 0,
        "definitionCount": 0,
        "resourceCount": 5
      }
    },
    {
      "path": "iac/provider-aws/main.tf",
      "language": "terraform",
      "fileCategory": "infra",
      "totalLines": 426,
      "nonEmptyLines": 353,
      "resources": [
        {
          "name": "random_password.volume_token_key",
          "kind": "random_password",
          "startLine": 63,
          "endLine": 70
        },
        {
          "name": "aws_security_group.cluster_node",
          "kind": "aws_security_group",
          "startLine": 371,
          "endLine": 426
        },
        {
          "name": "data.aws_region.current",
          "kind": "data.aws_region",
          "startLine": 43,
          "endLine": 43
        },
        {
          "name": "data.aws_caller_identity.current",
          "kind": "data.aws_caller_identity",
          "startLine": 45,
          "endLine": 45
        },
        {
          "name": "data.aws_elb_service_account.current",
          "kind": "data.aws_elb_service_account",
          "startLine": 47,
          "endLine": 47
        },
        {
          "name": "module.init",
          "kind": "module",
          "startLine": 49,
          "endLine": 61
        },
        {
          "name": "module.redis",
          "kind": "module",
          "startLine": 211,
          "endLine": 225
        },
        {
          "name": "module.cluster",
          "kind": "module",
          "startLine": 227,
          "endLine": 294
        },
        {
          "name": "module.nomad",
          "kind": "module",
          "startLine": 296,
          "endLine": 369
        }
      ],
      "metrics": {
        "importCount": 0,
        "exportCount": 0,
        "functionCount": 0,
        "classCount": 0,
        "definitionCount": 0,
        "resourceCount": 9
      }
    },
    {
      "path": "iac/provider-aws/moved.tf",
      "language": "terraform",
      "fileCategory": "infra",
      "totalLines": 4,
      "nonEmptyLines": 4,
      "metrics": {
        "importCount": 0,
        "exportCount": 0,
        "functionCount": 0,
        "classCount": 0,
        "definitionCount": 0,
        "resourceCount": 0
      }
    },
    {
      "path": "iac/provider-aws/variables.tf",
      "language": "terraform",
      "fileCategory": "infra",
      "totalLines": 249,
      "nonEmptyLines": 202,
      "definitions": [
        {
          "name": "domain_name",
          "kind": "variable",
          "fields": [],
          "startLine": 1,
          "endLine": 3
        },
        {
          "name": "allow_force_destroy",
          "kind": "variable",
          "fields": [],
          "startLine": 5,
          "endLine": 7
        },
        {
          "name": "prefix",
          "kind": "variable",
          "fields": [],
          "startLine": 9,
          "endLine": 12
        },
        {
          "name": "bucket_prefix",
          "kind": "variable",
          "fields": [],
          "startLine": 14,
          "endLine": 16
        },
        {
          "name": "environment",
          "kind": "variable",
          "fields": [],
          "startLine": 18,
          "endLine": 20
        },
        {
          "name": "redis_managed",
          "kind": "variable",
          "fields": [],
          "startLine": 22,
          "endLine": 25
        },
        {
          "name": "redis_instance_type",
          "kind": "variable",
          "fields": [],
          "startLine": 27,
          "endLine": 30
        },
        {
          "name": "redis_replica_size",
          "kind": "variable",
          "fields": [],
          "startLine": 32,
          "endLine": 35
        },
        {
          "name": "api_cluster_size",
          "kind": "variable",
          "fields": [],
          "startLine": 37,
          "endLine": 40
        },
        {
          "name": "api_internal_grpc_port",
          "kind": "variable",
          "fields": [],
          "startLine": 42,
          "endLine": 45
        },
        {
          "name": "api_env_vars",
          "kind": "variable",
          "fields": [],
          "startLine": 47,
          "endLine": 51
        },
        {
          "name": "api_db_migrator_env_vars",
          "kind": "variable",
          "fields": [],
          "startLine": 53,
          "endLine": 57
        },
        {
          "name": "client_proxy_env_vars",
          "kind": "variable",
          "fields": [],
          "startLine": 59,
          "endLine": 63
        },
        {
          "name": "orchestrator_env_vars",
          "kind": "variable",
          "fields": [],
          "startLine": 65,
          "endLine": 69
        },
        {
          "name": "template_manager_env_vars",
          "kind": "variable",
          "fields": [],
          "startLine": 71,
          "endLine": 75
        },
        {
          "name": "s3_use_path_style",
          "kind": "variable",
          "fields": [],
          "startLine": 77,
          "endLine": 81
        },
        {
          "name": "api_server_machine_type",
          "kind": "variable",
          "fields": [],
          "startLine": 83,
          "endLine": 86
        },
        {
          "name": "api_image_family_prefix",
          "kind": "variable",
          "fields": [],
          "startLine": 88,
          "endLine": 91
        },
        {
          "name": "ingress_count",
          "kind": "variable",
          "fields": [],
          "startLine": 93,
          "endLine": 96
        },
        {
          "name": "client_proxy_count",
          "kind": "variable",
          "fields": [],
          "startLine": 98,
          "endLine": 101
        },
        {
          "name": "clickhouse_cluster_size",
          "kind": "variable",
          "fields": [],
          "startLine": 103,
          "endLine": 106
        },
        {
          "name": "clickhouse_server_machine_type",
          "kind": "variable",
          "fields": [],
          "startLine": 108,
          "endLine": 111
        },
        {
          "name": "clickhouse_image_family_prefix",
          "kind": "variable",
          "fields": [],
          "startLine": 113,
          "endLine": 116
        },
        {
          "name": "client_cluster_size",
          "kind": "variable",
          "fields": [],
          "startLine": 118,
          "endLine": 121
        },
        {
          "name": "client_server_machine_type",
          "kind": "variable",
          "fields": [],
          "startLine": 123,
          "endLine": 126
        },
        {
          "name": "client_server_nested_virtualization",
          "kind": "variable",
          "fields": [],
          "startLine": 128,
          "endLine": 131
        },
        {
          "name": "client_node_labels",
          "kind": "variable",
          "fields": [],
          "startLine": 133,
          "endLine": 137
        },
        {
          "name": "client_image_family_prefix",
          "kind": "variable",
          "fields": [],
          "startLine": 139,
          "endLine": 142
        },
        {
          "name": "control_server_machine_type",
          "kind": "variable",
          "fields": [],
          "startLine": 144,
          "endLine": 147
        },
        {
          "name": "control_server_image_family_prefix",
          "kind": "variable",
          "fields": [],
          "startLine": 149,
          "endLine": 152
        },
        {
          "name": "orchestrator_port",
          "kind": "variable",
          "fields": [],
          "startLine": 154,
          "endLine": 157
        },
        {
          "name": "orchestrator_proxy_port",
          "kind": "variable",
          "fields": [],
          "startLine": 159,
          "endLine": 162
        },
        {
          "name": "allow_sandbox_internal_cidrs",
          "kind": "variable",
          "fields": [],
          "startLine": 164,
          "endLine": 168
        },
        {
          "name": "envd_timeout",
          "kind": "variable",
          "fields": [],
          "startLine": 170,
          "endLine": 173
        },
        {
          "name": "build_cluster_size",
          "kind": "variable",
          "fields": [],
          "startLine": 175,
          "endLine": 178
        },
        {
          "name": "build_server_machine_type",
          "kind": "variable",
          "fields": [],
          "startLine": 180,
          "endLine": 183
        },
        {
          "name": "build_server_nested_virtualization",
          "kind": "variable",
          "fields": [],
          "startLine": 185,
          "endLine": 188
        },
        {
          "name": "build_node_labels",
          "kind": "variable",
          "fields": [],
          "startLine": 190,
          "endLine": 194
        },
        {
          "name": "control_server_cluster_size",
          "kind": "variable",
          "fields": [],
          "startLine": 196,
          "endLine": 199
        },
        {
          "name": "traefik_config_files",
          "kind": "variable",
          "fields": [],
          "startLine": 201,
          "endLine": 205
        },
        {
          "name": "db_max_open_connections",
          "kind": "variable",
          "fields": [],
          "startLine": 207,
          "endLine": 210
        },
        {
          "name": "db_min_idle_connections",
          "kind": "variable",
          "fields": [],
          "startLine": 212,
          "endLine": 215
        },
        {
          "name": "auth_db_max_open_connections",
          "kind": "variable",
          "fields": [],
          "startLine": 217,
          "endLine": 220
        },
        {
          "name": "auth_db_min_idle_connections",
          "kind": "variable",
          "fields": [],
          "startLine": 222,
          "endLine": 225
        },
        {
          "name": "enable_otel_router_logs",
          "kind": "variable",
          "fields": [],
          "startLine": 227,
          "endLine": 231
        },
        {
          "name": "otel_router_http_port",
          "kind": "variable",
          "fields": [],
          "startLine": 233,
          "endLine": 237
        },
        {
          "name": "enable_otel_router_metrics",
          "kind": "variable",
          "fields": [],
          "startLine": 239,
          "endLine": 243
        },
        {
          "name": "otel_router_grpc_port",
          "kind": "variable",
          "fields": [],
          "startLine": 245,
          "endLine": 249
        }
      ],
      "metrics": {
        "importCount": 0,
        "exportCount": 0,
        "functionCount": 0,
        "classCount": 0,
        "definitionCount": 48,
        "resourceCount": 0
      }
    }
  ]
}